{"event_states": [{"actual_end_datetime": null, "actual_start_datetime": null, "aggregate": null, "clock": null, "has_league_table": false, "hidden": false, "id": "789305", "info": {"tennis_scoring_system": 3}, "instant_match": false, "match_period": "unknown", "probable_pitcher": null, "provider_metadata": null, "reversed": false, "scores": {"full": [2, 1], "sets": [{"score_a": 4, "score_b": 6}, {"score_a": 6, "score_b": 3}, {"score_a": 6, "score_b": 4}]}, "show_flags": null, "state": "ended", "tennis_server": null, "visualization": null}]}